{
  "schemaVersion": 1,
  "id": "fabricated_utility",
  "version": "${version}",

  "name": "Mod Name",
  "description": "wow mod thats incredible i love mods!",
  "authors": [
    {
      "name": "SimplyCmd",
      "contact": {
        "homepage": "https://simplycmd.github.io/"
      }
    },
    {
      "name": "Jab125",
      "contact": {
        "homepage": "https://www.jab125.com/"
      }
    }
  ],
  "contact": {
    "homepage": "https://simplycmd.github.io/",
    "sources": "https://github.com/SimplyCmd/"
  },

  "license": "MIT",
  "icon": "assets/fabricated_utility/icon.png",

  "environment": "*",
  "entrypoints": {
    "main": [
      "simplycmd.fabricated_utility.Main"
    ],
    "client": [
      "simplycmd.fabricated_utility.Main"
    ]
  },
  "mixins": [
    "fabricated_utility.mixins.json"
  ],
  "accessWidener" : "fabricated_utility.accesswidener",

  "depends": {
    "fabricloader": ">=0.11.3",
    "fabric": "*",
    "minecraft": "1.18.x",
    "java": ">=17"
  },
  "suggests": {
  }
}
